artemis.py
bcf_vcf.py
helper_functions.py
hmm_functions.py
main.py
make_mutationrate.py
make_test_data.py
hmmix-0.9.dist-info/LICENSE.txt
hmmix-0.9.dist-info/METADATA
hmmix-0.9.dist-info/WHEEL
hmmix-0.9.dist-info/entry_points.txt
hmmix-0.9.dist-info/top_level.txt
hmmix-0.9.dist-info/RECORD
