Metadata-Version: 2.1
Name: hmmix
Version: 0.9
Summary: Find introgressed segments
Home-page: https://github.com/LauritsSkov/Introgression-detection
Author: Laurits Skov and Moises Coll Macia
Author-email: lauritsskov2@gmail.com
Classifier: Programming Language :: Python :: 3
Classifier: Programming Language :: Python :: 3.5
Classifier: Programming Language :: Python :: 3.6
Classifier: Programming Language :: Python :: 3.7
Classifier: Programming Language :: Python :: 3.8
Classifier: Programming Language :: Python :: 3.9
Classifier: License :: OSI Approved :: MIT License
Requires-Python: >3.5, <3.11
License-File: LICENSE.txt
Requires-Dist: numpy>=1.15
Requires-Dist: scipy>=1.5
Requires-Dist: matplotlib>=3.3
Requires-Dist: numba
